{"name":"show_result_of_additional_between_two_numbers","id":"LearningSerenity.features.search.ImplementCaculatorFunction:show_result_of_additional_between_two_numbers","testCaseName":"LearningSerenity.features.search.ImplementCaculatorFunction","testSteps":[{"number":1,"description":"Open the application","duration":419,"startTime":"2020-05-02T21:46:20.014661200+07:00[Asia/Saigon]","precondition":false,"level":0,"children":[{"number":2,"description":"anna opens the Caculator online page","duration":399,"startTime":"2020-05-02T21:46:20.031615400+07:00[Asia/Saigon]","exception":{"errorType":"net.thucydides.core.webdriver.DriverConfigurationError","message":"Could not instantiate class org.openqa.selenium.chrome.ChromeDriver","stackTrace":[{"classLoaderName":"app","declaringClass":"LearningSerenity.tasks.OpenCaculatorTool","methodName":"performAs","fileName":"OpenCaculatorTool.java","lineNumber":14,"format":1},{"classLoaderName":"app","declaringClass":"LearningSerenity.features.search.ImplementCaculatorFunction","methodName":"show_result_of_additional_between_two_numbers","fileName":"ImplementCaculatorFunction.java","lineNumber":28,"format":1}],"rootCause":{"errorType":"net.thucydides.core.webdriver.DriverConfigurationError","message":"Could not instantiate new WebDriver instance of type class org.openqa.selenium.chrome.ChromeDriver (The driver executable is a directory: E:\\chromedriver\\Driver). See below for more details.","stackTrace":[{"classLoaderName":"app","declaringClass":"LearningSerenity.tasks.OpenCaculatorTool","methodName":"performAs","fileName":"OpenCaculatorTool.java","lineNumber":14,"format":1},{"classLoaderName":"app","declaringClass":"LearningSerenity.features.search.ImplementCaculatorFunction","methodName":"show_result_of_additional_between_two_numbers","fileName":"ImplementCaculatorFunction.java","lineNumber":28,"format":1}],"rootCause":{"errorType":"java.lang.IllegalStateException","message":"The driver executable is a directory: E:\\chromedriver\\Driver","stackTrace":[{"classLoaderName":"app","declaringClass":"com.google.common.base.Preconditions","methodName":"checkState","fileName":"Preconditions.java","lineNumber":585,"format":1},{"classLoaderName":"app","declaringClass":"LearningSerenity.tasks.OpenCaculatorTool","methodName":"performAs","fileName":"OpenCaculatorTool.java","lineNumber":14,"format":1},{"classLoaderName":"app","declaringClass":"LearningSerenity.features.search.ImplementCaculatorFunction","methodName":"show_result_of_additional_between_two_numbers","fileName":"ImplementCaculatorFunction.java","lineNumber":28,"format":1}]}}},"result":"ERROR","precondition":false,"level":1}]}],"userStory":{"id":"LearningSerenity.features.search.ImplementCaculatorFunction","storyName":"Implement caculator function","storyClassName":"LearningSerenity.features.search.ImplementCaculatorFunction","path":"search","type":"story"},"featureTag":{"name":"Search/Implement caculator function","type":"story","displayName":"Search/Implement caculator function"},"title":"Show result of additional between two numbers","tags":[{"name":"Search/Implement caculator function","type":"story","displayName":"Search/Implement caculator function"},{"name":"Search","type":"feature","displayName":"Search"}],"startTime":"2020-05-02T21:46:19.688626700+07:00[Asia/Saigon]","duration":757,"testFailureCause":{"errorType":"java.lang.IllegalArgumentException","message":"Could not find a matching constructor for class class LearningSerenity.tasks.AddTwoNumbers with parameters [add, 6, 4]","stackTrace":[{"classLoaderName":"app","declaringClass":"LearningSerenity.features.search.ImplementCaculatorFunction","methodName":"show_result_of_additional_between_two_numbers","fileName":"ImplementCaculatorFunction.java","lineNumber":30,"format":1}]},"testFailureClassname":"java.lang.IllegalArgumentException","testFailureMessage":"Could not find a matching constructor for class class LearningSerenity.tasks.AddTwoNumbers with parameters [add, 6, 4]","testFailureSummary":"ERROR;java.lang.IllegalArgumentException;Could not find a matching constructor for class class LearningSerenity.tasks.AddTwoNumbers with parameters [add, 6, 4];ImplementCaculatorFunction.java","projectKey":"","annotatedResult":"ERROR","driver":"","isManualTestingUpToDate":false,"manual":false,"testSource":"JUnit","actors":[{"name":"anna","can":["browse the web"]}],"result":"ERROR"}